ProximityUI/ProximityUI.py
ProximityUI/__init__.py
ProximityUI-1.0.dist-info/LICENSE.txt
ProximityUI-1.0.dist-info/METADATA
ProximityUI-1.0.dist-info/WHEEL
ProximityUI-1.0.dist-info/top_level.txt
ProximityUI-1.0.dist-info/RECORD
