Metadata-Version: 2.1
Name: ProximityUI
Version: 1.0
Summary: library code execute various proximity analyses using ArcPy
Home-page: https://github.com/ProvidenceAdu/ProximityUI
Author: Providence Adu,Ph.D.
Author-email: <padu@charlotte.edu>
Keywords: urban institute,python,QOL,quality of life explorer
License-File: LICENSE.txt
Requires-Dist: numpy (>=1.18.0)
Requires-Dist: pandas (>=1.0.0)
